aqueduct3/__init__.py
aqueduct3/aqueduct3.py
aqueduct3/cli.py
aqueduct3-0.1.1.dist-info/DESCRIPTION.rst
aqueduct3-0.1.1.dist-info/METADATA
aqueduct3-0.1.1.dist-info/RECORD
aqueduct3-0.1.1.dist-info/WHEEL
aqueduct3-0.1.1.dist-info/entry_points.txt
aqueduct3-0.1.1.dist-info/metadata.json
aqueduct3-0.1.1.dist-info/top_level.txt
