Metadata-Version: 2.0
Name: aqueduct3
Version: 0.1.1
Summary: Python module for aqueduct program.
Home-page: https://github.com/rutgerhofste/aqueduct3
Author: Rutger Hofste
Author-email: rutgerhofste@gmail.com
License: MIT license
Keywords: aqueduct3
Platform: UNKNOWN
Classifier: Development Status :: 2 - Pre-Alpha
Classifier: Intended Audience :: Developers
Classifier: License :: OSI Approved :: MIT License
Classifier: Natural Language :: English
Classifier: Programming Language :: Python :: 2
Classifier: Programming Language :: Python :: 2.7
Classifier: Programming Language :: Python :: 3
Classifier: Programming Language :: Python :: 3.4
Classifier: Programming Language :: Python :: 3.5
Classifier: Programming Language :: Python :: 3.6
Requires-Dist: Click (>=6.0)
